gfn/__init__.py
gfn/actions.py
gfn/containers/__init__.py
gfn/containers/base.py
gfn/containers/message.py
gfn/containers/replay_buffer.py
gfn/containers/replay_buffer_manager.py
gfn/containers/states_container.py
gfn/containers/trajectories.py
gfn/containers/transitions.py
gfn/env.py
gfn/estimators.py
gfn/gflownet/__init__.py
gfn/gflownet/base.py
gfn/gflownet/detailed_balance.py
gfn/gflownet/flow_matching.py
gfn/gflownet/sub_trajectory_balance.py
gfn/gflownet/trajectory_balance.py
gfn/gym/__init__.py
gfn/gym/bayesian_structure.py
gfn/gym/bitSequence.py
gfn/gym/box.py
gfn/gym/diffusion_sampling.py
gfn/gym/discrete_ebm.py
gfn/gym/graph_building.py
gfn/gym/helpers/__init__.py
gfn/gym/helpers/bayesian_structure/__init__.py
gfn/gym/helpers/bayesian_structure/evaluation.py
gfn/gym/helpers/bayesian_structure/factories.py
gfn/gym/helpers/bayesian_structure/graph.py
gfn/gym/helpers/bayesian_structure/jsd.py
gfn/gym/helpers/bayesian_structure/priors.py
gfn/gym/helpers/bayesian_structure/sampling.py
gfn/gym/helpers/bayesian_structure/scores.py
gfn/gym/helpers/box_utils.py
gfn/gym/helpers/diffusion_utils.py
gfn/gym/hypergrid.py
gfn/gym/line.py
gfn/gym/perfect_tree.py
gfn/gym/set_addition.py
gfn/gym/tests/test_box_utils.py
gfn/modules.py
gfn/preprocessors.py
gfn/samplers.py
gfn/states.py
gfn/utils/__init__.py
gfn/utils/common.py
gfn/utils/distributed.py
gfn/utils/distributions.py
gfn/utils/graphs.py
gfn/utils/handlers.py
gfn/utils/modules.py
gfn/utils/prob_calculations.py
gfn/utils/training.py
torchgfn-2.3.0.dist-info/METADATA
torchgfn-2.3.0.dist-info/WHEEL
torchgfn-2.3.0.dist-info/licenses/LICENSE
torchgfn-2.3.0.dist-info/RECORD
