Metadata-Version: 2.4
Name: torchgfn
Version: 2.3.0
Summary: A torch implementation of GFlowNets
License: MIT
License-File: LICENSE
Author: Salem Lahlou
Author-email: salemlahlou9@gmail.com
Requires-Python: >=3.10,<4.0
Classifier: License :: OSI Approved :: MIT License
Classifier: Operating System :: OS Independent
Classifier: Programming Language :: Python :: 3
Classifier: Programming Language :: Python :: 3.10
Classifier: Programming Language :: Python :: 3.11
Classifier: Programming Language :: Python :: 3.12
Classifier: Programming Language :: Python :: 3.13
Classifier: Programming Language :: Python :: 3.14
Provides-Extra: all
Provides-Extra: dev
Provides-Extra: scripts
Requires-Dist: black (==2.3.0) ; extra == "dev" or extra == "all"
Requires-Dist: dill (>=0.3.8)
Requires-Dist: einops (>=0.6.1)
Requires-Dist: flake8 (==2.3.0) ; extra == "dev" or extra == "all"
Requires-Dist: gitmopy (==2.3.0) ; extra == "dev" or extra == "all"
Requires-Dist: insegel (==2.3.0) ; extra == "dev" or extra == "all"
Requires-Dist: isort (==2.3.0) ; extra == "dev" or extra == "all"
Requires-Dist: linear-attention-transformer (>=0.19.1)
Requires-Dist: matplotlib (==2.3.0) ; extra == "scripts" or extra == "all"
Requires-Dist: myst-parser (==2.3.0) ; extra == "dev" or extra == "all"
Requires-Dist: nbmake (==2.3.0) ; extra == "dev" or extra == "all"
Requires-Dist: networkx (==2.3.0) ; extra == "scripts" or extra == "all"
Requires-Dist: numpy (<2)
Requires-Dist: pgmpy (==2.3.0) ; extra == "scripts" or extra == "all"
Requires-Dist: pre-commit (==2.3.0) ; extra == "dev" or extra == "all"
Requires-Dist: pyright (==2.3.0) ; extra == "dev" or extra == "all"
Requires-Dist: pytest (==2.3.0) ; extra == "dev" or extra == "all"
Requires-Dist: renku-sphinx-theme (==2.3.0) ; extra == "dev" or extra == "all"
Requires-Dist: scikit-learn (==2.3.0) ; extra == "scripts" or extra == "all"
Requires-Dist: scipy (==2.3.0) ; extra == "scripts" or extra == "all"
Requires-Dist: seaborn (==2.3.0) ; extra == "scripts" or extra == "all"
Requires-Dist: sphinx (==2.3.0) ; extra == "dev" or extra == "all"
Requires-Dist: sphinx-autoapi (==2.3.0) ; extra == "dev" or extra == "all"
Requires-Dist: sphinx-math-dollar (==2.3.0) ; extra == "dev" or extra == "all"
Requires-Dist: sphinx_rtd_theme (==2.3.0) ; extra == "dev" or extra == "all"
Requires-Dist: tensordict (>=0.6.1)
Requires-Dist: torch (>=2.6.0)
Requires-Dist: torch_geometric (>=2.6.1)
Requires-Dist: tox (==2.3.0) ; extra == "dev" or extra == "all"
Requires-Dist: tqdm (==2.3.0) ; extra == "scripts" or extra == "all"
Requires-Dist: wandb (==2.3.0) ; extra == "scripts" or extra == "all"
Project-URL: Bug Tracker, https://github.com/gfnorg/torchgfn/issues
Project-URL: Homepage, https://gfn.readthedocs.io/en/latest/
